planc_core/__init__.py
planc_core/main.py
planc_core/py.typed
planc_core-0.0.1.dev20251208210149.dist-info/WHEEL
planc_core-0.0.1.dev20251208210149.dist-info/METADATA
planc_core-0.0.1.dev20251208210149.dist-info/RECORD
