Metadata-Version: 2.3
Name: planc-core
Version: 0.0.1.dev20251208210149
Summary: Add your description here
Requires-Dist: requests>=2.32.5
